[
  {
    "from": "Me",
    "to": "you",
    "message": "I hate you",
    "reference": "300"
  },
  {
    "from": "Me",
    "to": "you",
    "message": "I hate you",
    "reference": "3001"
  },
  {
    "from": "",
    "to": "",
    "message": "",
    "reference": 0
  },
  {
    "from": "sss",
    "to": "sss",
    "message": "sss",
    "reference": "2"
  },
  {
    "from": "sss",
    "to": "sss",
    "message": "sss",
    "reference": "4"
  },
  {
    "from": "sss",
    "to": "sss",
    "message": "sss",
    "reference": "5"
  }
]